tool_server_generator/__init__.py
tool_server_generator/examples/config_server.json
tool_server_generator/examples/config_server.txt
tool_server_generator/examples/config_server2.txt
tool_server_generator/model/app.js
tool_server_generator/model/package-lock.json
tool_server_generator/model/package.json
tool_server_generator/model/bin/www
tool_server_generator/model/public/images/favicon.ico
tool_server_generator/model/public/javascripts/jquery.js
tool_server_generator/model/public/javascripts/requests.js
tool_server_generator/model/public/stylesheets/color.css
tool_server_generator/model/public/stylesheets/w3.css
tool_server_generator/model/routes/index.js
tool_server_generator/model/views/error.pug
tool_server_generator/model/views/layout.pug
tool_server_generator/model/views/requests.pug
tool_server_generator/model/workers/process_command.js
tool_server_generator/model/workers/request_listener.js
tool_server_generator/utils/config_parser.py
tool_server_generator/utils/config_server.py
tool_server_generator/utils/utils.py
tool_server_generator-0.4.4.dist-info/entry_points.txt
tool_server_generator-0.4.4.dist-info/LICENSE
tool_server_generator-0.4.4.dist-info/WHEEL
tool_server_generator-0.4.4.dist-info/METADATA
tool_server_generator-0.4.4.dist-info/RECORD
